whispercpp_py-0.0.23.dist-info/METADATA
whispercpp_py-0.0.23.dist-info/RECORD
whispercpp_py-0.0.23.dist-info/WHEEL
whispercpp_py/__init__.py
whispercpp_py/__init__.pyi
whispercpp_py/api.pyi
whispercpp_py/api_cpp2py_export.so
whispercpp_py/audio.pyi
whispercpp_py/audio_cpp2py_export.so
whispercpp_py/utils.py
